storm_modules/__init__.py
storm_modules/cli_args.py
tests/__init__.py
tests/common.py
storm_modules-1.0.dist-info/METADATA
storm_modules-1.0.dist-info/WHEEL
storm_modules-1.0.dist-info/top_level.txt
storm_modules-1.0.dist-info/RECORD
